odoo/addons/stock_production_lot_traceability/README.rst
odoo/addons/stock_production_lot_traceability/__init__.py
odoo/addons/stock_production_lot_traceability/__manifest__.py
odoo/addons/stock_production_lot_traceability/i18n/stock_production_lot_traceability.pot
odoo/addons/stock_production_lot_traceability/models/__init__.py
odoo/addons/stock_production_lot_traceability/models/stock_move_line.py
odoo/addons/stock_production_lot_traceability/models/stock_production_lot.py
odoo/addons/stock_production_lot_traceability/readme/CONTRIBUTORS.rst
odoo/addons/stock_production_lot_traceability/readme/DESCRIPTION.rst
odoo/addons/stock_production_lot_traceability/readme/USAGE.rst
odoo/addons/stock_production_lot_traceability/static/description/icon.png
odoo/addons/stock_production_lot_traceability/static/description/index.html
odoo/addons/stock_production_lot_traceability/tests/__init__.py
odoo/addons/stock_production_lot_traceability/tests/common.py
odoo/addons/stock_production_lot_traceability/tests/test_stock_lot_traceability.py
odoo/addons/stock_production_lot_traceability/views/stock_production_lot.xml
odoo12_addon_stock_production_lot_traceability-12.0.1.0.1.dist-info/METADATA
odoo12_addon_stock_production_lot_traceability-12.0.1.0.1.dist-info/WHEEL
odoo12_addon_stock_production_lot_traceability-12.0.1.0.1.dist-info/top_level.txt
odoo12_addon_stock_production_lot_traceability-12.0.1.0.1.dist-info/RECORD
